oneNeuron/__init__.py
oneNeuron/perceptron.py
oneNeuron_pkg_kuchbhiarnav-0.0.4.dist-info/LICENSE
oneNeuron_pkg_kuchbhiarnav-0.0.4.dist-info/METADATA
oneNeuron_pkg_kuchbhiarnav-0.0.4.dist-info/WHEEL
oneNeuron_pkg_kuchbhiarnav-0.0.4.dist-info/top_level.txt
oneNeuron_pkg_kuchbhiarnav-0.0.4.dist-info/RECORD
